jailbreakeval/__init__.py
jailbreakeval/utils.py
jailbreakeval/commands/__init__.py
jailbreakeval/commands/main.py
jailbreakeval/configurations/__init__.py
jailbreakeval/configurations/chat_configuration.py
jailbreakeval/configurations/configuration_base.py
jailbreakeval/configurations/string_matching_configuration.py
jailbreakeval/configurations/text_classifier_configuration.py
jailbreakeval/configurations/voting_configuration.py
jailbreakeval/evaluators/__init__.py
jailbreakeval/evaluators/chat_evaluator.py
jailbreakeval/evaluators/evaluator_base.py
jailbreakeval/evaluators/string_matching_evaluator.py
jailbreakeval/evaluators/text_classification_evaluator.py
jailbreakeval/evaluators/types.py
jailbreakeval/evaluators/voting_evaluator.py
jailbreakeval/presets/HFChat-dubey2024llama-llamaguard3.yaml
jailbreakeval/presets/HFChat-inan2023llama-llamaguard.yaml
jailbreakeval/presets/HFChat-inan2023llama-llamaguard2.yaml
jailbreakeval/presets/HFTextClassification-ji2023beavertails-beaver-dam-7b.yaml
jailbreakeval/presets/HFTextClassification-wang2023donotanswer-longformer-action.yaml
jailbreakeval/presets/HFTextClassification-wang2023donotanswer-longformer-harmful.yaml
jailbreakeval/presets/HFTextClassification-yu2023gptfuzzer-GPTFuzz.yaml
jailbreakeval/presets/OpenAIChat-liu2024autodan-Recheck.yaml
jailbreakeval/presets/OpenAIChat-qi2023fine-Meta.yaml
jailbreakeval/presets/OpenAIChat-qi2023fine-OpenAI.yaml
jailbreakeval/presets/OpenAIChat-zhang2024intention-LLM.yaml
jailbreakeval/presets/OpenAITextClassification-flagged-answer.yaml
jailbreakeval/presets/PerspectiveTextClassification-toxicity.yaml
jailbreakeval/presets/StringMatching-lapid2023open.yaml
jailbreakeval/presets/StringMatching-liu2024autodan-implementation.yaml
jailbreakeval/presets/StringMatching-liu2024autodan-keyword.yaml
jailbreakeval/presets/StringMatching-zhang2024intention-keyword.yaml
jailbreakeval/presets/StringMatching-zou2023universal-closed.yaml
jailbreakeval-0.0.4.dist-info/METADATA
jailbreakeval-0.0.4.dist-info/WHEEL
jailbreakeval-0.0.4.dist-info/entry_points.txt
jailbreakeval-0.0.4.dist-info/licenses/LICENSE
jailbreakeval-0.0.4.dist-info/RECORD
