Metadata-Version: 2.4
Name: jailbreakeval
Version: 0.0.4
Summary: A collection of automated evaluators for assessing jailbreak attempts
Project-URL: Homepage, https://github.com/ThuCCSLab/JailbreakEval
Project-URL: Issues, https://github.com/ThuCCSLab/JailbreakEval/issues
Author-email: Delong Ran <rdl22@mails.tsinghua.edu.cn>
License-File: LICENSE
Classifier: License :: OSI Approved :: MIT License
Classifier: Programming Language :: Python :: 3
Requires-Python: >=3.9
Requires-Dist: accelerate
Requires-Dist: click
Requires-Dist: google-api-python-client
Requires-Dist: jinja2
Requires-Dist: numpy
Requires-Dist: openai>=1.49.0
Requires-Dist: pandas
Requires-Dist: prettytable
Requires-Dist: pyyaml
Requires-Dist: scikit-learn
Requires-Dist: sentencepiece
Requires-Dist: torch
Requires-Dist: tqdm
Requires-Dist: transformers>=4.45.0
Provides-Extra: test
Requires-Dist: pytest; extra == 'test'
Requires-Dist: pytest-cov; extra == 'test'
